LICENSE
MANIFEST.in
README.rst
setup.cfg
setup.py
aioamqp_consumer/__init__.py
aioamqp_consumer/amqp.py
aioamqp_consumer/consumer.py
aioamqp_consumer/exceptions.py
aioamqp_consumer/log.py
aioamqp_consumer/packer.py
aioamqp_consumer/producer.py
aioamqp_consumer/rpc.py
aioamqp_consumer/run.py
aioamqp_consumer/settings.py
aioamqp_consumer/utils.py
aioamqp_consumer.egg-info/PKG-INFO
aioamqp_consumer.egg-info/SOURCES.txt
aioamqp_consumer.egg-info/dependency_links.txt
aioamqp_consumer.egg-info/not-zip-safe
aioamqp_consumer.egg-info/requires.txt
aioamqp_consumer.egg-info/top_level.txt