Metadata-Version: 1.2
Name: aioamqp-consumer
Version: 0.2.0
Summary: consumer/producer/rpc library built over aioamqp
Home-page: https://github.com/aio-libs/aioamqp_consumer
Author: OCEAN S.A.
Author-email: hellysmile@gmail.com
License: UNKNOWN
Keywords: amqp,asyncio,aioamqp,consumer,producer,rpc
Platform: UNKNOWN
Classifier: Development Status :: 4 - Beta
Classifier: Intended Audience :: Developers
Classifier: License :: OSI Approved :: MIT License
Classifier: Operating System :: POSIX
Classifier: Operating System :: MacOS :: MacOS X
Classifier: Operating System :: Microsoft :: Windows
Classifier: Programming Language :: Python
Classifier: Programming Language :: Python :: 3
Classifier: Programming Language :: Python :: 3.6
Classifier: Programming Language :: Python :: 3.7
Classifier: Programming Language :: Python :: 3.8
Requires-Python: >=3.6.0
